{"member":[{"id":0,"name":"Cecile Walker DDS","avatar":"https://s3.amazonaws.com/uifaces/faces/twitter/adhiardana/128.jpg","title":"District Assurance Strategist","day_start":84,"day_end":12,"follower":459,"following":883,"reviews":197},{"id":1,"name":"Mr. Luella Rau","avatar":"https://s3.amazonaws.com/uifaces/faces/twitter/adityasutomo/128.jpg","title":"Customer Factors Specialist","day_start":53,"day_end":41,"follower":129,"following":105,"reviews":969},{"id":2,"name":"Tabitha Harber","avatar":"https://s3.amazonaws.com/uifaces/faces/twitter/looneydoodle/128.jpg","title":"Principal Group Architect","day_start":8,"day_end":84,"follower":933,"following":708,"reviews":374},{"id":3,"name":"Devin Terry","avatar":"https://s3.amazonaws.com/uifaces/faces/twitter/kostaspt/128.jpg","title":"Senior Functionality Liason","day_start":35,"day_end":10,"follower":180,"following":761,"reviews":721},{"id":4,"name":"Armani Nikolaus DVM","avatar":"https://s3.amazonaws.com/uifaces/faces/twitter/rehatkathuria/128.jpg","title":"Chief Communications Coordinator","day_start":17,"day_end":46,"follower":465,"following":403,"reviews":935},{"id":5,"name":"Gina Medhurst","avatar":"https://s3.amazonaws.com/uifaces/faces/twitter/jitachi/128.jpg","title":"Global Operations Technician","day_start":33,"day_end":10,"follower":358,"following":547,"reviews":716},{"id":6,"name":"Eda Brown","avatar":"https://s3.amazonaws.com/uifaces/faces/twitter/we_social/128.jpg","title":"Future Identity Consultant","day_start":73,"day_end":33,"follower":211,"following":762,"reviews":673},{"id":7,"name":"Michaela O'Keefe","avatar":"https://s3.amazonaws.com/uifaces/faces/twitter/adhamdannaway/128.jpg","title":"Dynamic Marketing Representative","day_start":77,"day_end":17,"follower":381,"following":802,"reviews":274},{"id":8,"name":"Vernie Sauer","avatar":"https://s3.amazonaws.com/uifaces/faces/twitter/bereto/128.jpg","title":"Future Directives Representative","day_start":60,"day_end":44,"follower":61,"following":207,"reviews":902},{"id":9,"name":"Brannon Hyatt","avatar":"https://s3.amazonaws.com/uifaces/faces/twitter/desastrozo/128.jpg","title":"Human Mobility Designer","day_start":72,"day_end":89,"follower":939,"following":764,"reviews":212},{"id":10,"name":"Nathaniel Collins","avatar":"https://s3.amazonaws.com/uifaces/faces/twitter/mattlat/128.jpg","title":"Forward Communications Analyst","day_start":49,"day_end":73,"follower":521,"following":786,"reviews":362},{"id":11,"name":"Dr. Luciano Jacobson","avatar":"https://s3.amazonaws.com/uifaces/faces/twitter/jerrybai1907/128.jpg","title":"Human Brand Engineer","day_start":10,"day_end":30,"follower":325,"following":249,"reviews":153},{"id":12,"name":"Miss Ellis Green","avatar":"https://s3.amazonaws.com/uifaces/faces/twitter/bryan_topham/128.jpg","title":"Senior Accountability Strategist","day_start":26,"day_end":69,"follower":142,"following":694,"reviews":760},{"id":13,"name":"Yvonne Sauer","avatar":"https://s3.amazonaws.com/uifaces/faces/twitter/bereto/128.jpg","title":"Internal Implementation Analyst","day_start":1,"day_end":74,"follower":935,"following":763,"reviews":320},{"id":14,"name":"Bradford Harber","avatar":"https://s3.amazonaws.com/uifaces/faces/twitter/amywebbb/128.jpg","title":"Human Accountability Consultant","day_start":35,"day_end":61,"follower":609,"following":411,"reviews":691},{"id":15,"name":"Timmy Nienow I","avatar":"https://s3.amazonaws.com/uifaces/faces/twitter/sebashton/128.jpg","title":"Central Data Strategist","day_start":19,"day_end":77,"follower":674,"following":898,"reviews":314},{"id":16,"name":"Tomas Sawayn","avatar":"https://s3.amazonaws.com/uifaces/faces/twitter/herkulano/128.jpg","title":"Chief Division Engineer","day_start":1,"day_end":68,"follower":740,"following":48,"reviews":857},{"id":17,"name":"Mr. Mia Graham","avatar":"https://s3.amazonaws.com/uifaces/faces/twitter/m_kalibry/128.jpg","title":"Product Operations Administrator","day_start":74,"day_end":65,"follower":716,"following":428,"reviews":438},{"id":18,"name":"Royal Herzog","avatar":"https://s3.amazonaws.com/uifaces/faces/twitter/nicoleglynn/128.jpg","title":"Future Assurance Architect","day_start":17,"day_end":42,"follower":443,"following":589,"reviews":109},{"id":19,"name":"Drew Crooks DVM","avatar":"https://s3.amazonaws.com/uifaces/faces/twitter/marcomano_/128.jpg","title":"Future Security Supervisor","day_start":54,"day_end":6,"follower":395,"following":118,"reviews":789},{"id":20,"name":"Xavier Tromp","avatar":"https://s3.amazonaws.com/uifaces/faces/twitter/johnsmithagency/128.jpg","title":"International Assurance Specialist","day_start":18,"day_end":7,"follower":181,"following":239,"reviews":474},{"id":21,"name":"Laron Mertz","avatar":"https://s3.amazonaws.com/uifaces/faces/twitter/danpliego/128.jpg","title":"Product Functionality Technician","day_start":77,"day_end":28,"follower":771,"following":854,"reviews":126},{"id":22,"name":"Barry Friesen","avatar":"https://s3.amazonaws.com/uifaces/faces/twitter/vanchesz/128.jpg","title":"Legacy Interactions Representative","day_start":16,"day_end":88,"follower":101,"following":119,"reviews":946},{"id":23,"name":"Ansley Smitham","avatar":"https://s3.amazonaws.com/uifaces/faces/twitter/d_nny_m_cher/128.jpg","title":"Chief Infrastructure Orchestrator","day_start":37,"day_end":68,"follower":454,"following":86,"reviews":439},{"id":24,"name":"Demond Cartwright","avatar":"https://s3.amazonaws.com/uifaces/faces/twitter/kalmerrautam/128.jpg","title":"International Functionality Designer","day_start":6,"day_end":82,"follower":983,"following":726,"reviews":260},{"id":25,"name":"Adelle Labadie III","avatar":"https://s3.amazonaws.com/uifaces/faces/twitter/buddhasource/128.jpg","title":"Regional Group Liason","day_start":79,"day_end":61,"follower":515,"following":571,"reviews":288},{"id":26,"name":"Grace Stamm","avatar":"https://s3.amazonaws.com/uifaces/faces/twitter/nasirwd/128.jpg","title":"Investor Response Consultant","day_start":75,"day_end":86,"follower":711,"following":41,"reviews":718},{"id":27,"name":"Waino Lueilwitz","avatar":"https://s3.amazonaws.com/uifaces/faces/twitter/dotgridline/128.jpg","title":"Investor Communications Planner","day_start":34,"day_end":61,"follower":956,"following":344,"reviews":39},{"id":28,"name":"Lennie Dietrich","avatar":"https://s3.amazonaws.com/uifaces/faces/twitter/daniloc/128.jpg","title":"Direct Branding Associate","day_start":20,"day_end":43,"follower":878,"following":443,"reviews":737},{"id":29,"name":"Kenyon Boyle PhD","avatar":"https://s3.amazonaws.com/uifaces/faces/twitter/svenlen/128.jpg","title":"Future Implementation Developer","day_start":13,"day_end":5,"follower":294,"following":325,"reviews":827}]}